convtools/_chunks.py
convtools/_base.py
convtools/_mutations.py
convtools/_joins.py
convtools/_dt.py
convtools/_conversion.py
convtools/_aggregations.py
convtools/_heuristics.py
convtools/_cext.cpython-314t-darwin.so
convtools/__init__.py
convtools/_ordering.py
convtools/_columns.py
convtools/_unique.py
convtools/_debug.py
convtools/_window.py
convtools/_try.py
convtools/_exceptions.py
convtools/_optimizer.py
convtools/_cumulative.py
convtools/_expect.py
convtools/_utils.py
convtools/contrib/__init__.py
convtools/contrib/fs.py
convtools/contrib/tables.py
convtools/c_extensions/getters.c
convtools-1.17.0.dist-info/RECORD
convtools-1.17.0.dist-info/WHEEL
convtools-1.17.0.dist-info/top_level.txt
convtools-1.17.0.dist-info/METADATA
convtools-1.17.0.dist-info/licenses/LICENSE.txt
