Metadata-Version: 2.4
Name: convtools
Version: 1.17.0
Summary: dynamic, declarative data transformations with automatic code generation
Author-email: Nikita Almakov <nikita.almakov@gmail.com>
Maintainer-email: Nikita Almakov <nikita.almakov@gmail.com>
License: The MIT License (MIT)
Project-URL: homepage, https://github.com/westandskif/convtools
Project-URL: documentation, https://convtools.readthedocs.io/en/latest/
Project-URL: repository, https://github.com/westandskif/convtools
Project-URL: changelog, https://github.com/westandskif/convtools/blob/master/docs/changelog.md
Keywords: etl,converters,codegen,convtools
Classifier: Development Status :: 5 - Production/Stable
Classifier: Intended Audience :: Developers
Classifier: License :: OSI Approved :: MIT License
Classifier: Operating System :: OS Independent
Classifier: Programming Language :: Python
Classifier: Programming Language :: Python :: 3 :: Only
Classifier: Programming Language :: Python :: 3.6
Classifier: Programming Language :: Python :: 3.7
Classifier: Programming Language :: Python :: 3.8
Classifier: Programming Language :: Python :: 3.9
Classifier: Programming Language :: Python :: 3.10
Classifier: Programming Language :: Python :: 3.11
Classifier: Programming Language :: Python :: 3.12
Classifier: Programming Language :: Python :: 3.13
Classifier: Programming Language :: Python :: 3.14
Classifier: Topic :: Software Development :: Code Generators
Classifier: Topic :: Software Development :: Libraries
Classifier: Topic :: Software Development :: Libraries :: Python Modules
Classifier: Topic :: Utilities
Requires-Python: >=3.6
License-File: LICENSE.txt
Requires-Dist: astunparse==1.6.3; python_version < "3.9"
Provides-Extra: test
Requires-Dist: pytest; extra == "test"
Requires-Dist: pytest-cov; extra == "test"
Requires-Dist: pytest-benchmark; extra == "test"
Provides-Extra: lint
Requires-Dist: black; extra == "lint"
Requires-Dist: flake8; extra == "lint"
Requires-Dist: isort; extra == "lint"
Requires-Dist: mypy; extra == "lint"
Requires-Dist: pylint; extra == "lint"
Provides-Extra: doc
Requires-Dist: markdown-include; extra == "doc"
Requires-Dist: mdx-truly-sane-lists; extra == "doc"
Requires-Dist: mkdocs; extra == "doc"
Requires-Dist: mkdocs-exclude; extra == "doc"
Requires-Dist: mkdocs-material; extra == "doc"
Requires-Dist: pygments; extra == "doc"
Requires-Dist: pymdown-extensions; extra == "doc"
Dynamic: license-file
